prangoncalculator/__init__.py
prangoncalculator/calculator.py
prangoncalculator-0.0.2.dist-info/LICENSE
prangoncalculator-0.0.2.dist-info/METADATA
prangoncalculator-0.0.2.dist-info/WHEEL
prangoncalculator-0.0.2.dist-info/top_level.txt
prangoncalculator-0.0.2.dist-info/RECORD
