Metadata-Version: 2.1
Name: prangoncalculator
Version: 0.0.2
Summary: this is very basic calculator
Home-page: UNKNOWN
Author: prangon
Author-email: 1001080@daffodil.ac
License: UNKNOWN
Platform: UNKNOWN
License-File: LICENSE
